code_domain_emissary/__init__.py
code_domain_emissary/handlers.py
CodeDomainEmissary-0.0.1.dev0.dist-info/METADATA
CodeDomainEmissary-0.0.1.dev0.dist-info/WHEEL
CodeDomainEmissary-0.0.1.dev0.dist-info/top_level.txt
CodeDomainEmissary-0.0.1.dev0.dist-info/RECORD
