Metadata-Version: 2.1
Name: CodeDomainEmissary
Version: 0.0.1.dev0
Summary: A package to adapt text to code domain intents and entities
Home-page: UNKNOWN
Author: Colin Lacy
Author-email: colinjlacy@gmail.com
License: UNKNOWN
Platform: UNKNOWN
Classifier: Programming Language :: Python :: 3.6
Classifier: License :: OSI Approved :: GNU General Public License v3 (GPLv3)
Requires-Dist: mindmeld (>=4.1.1)
